drcrypt/__init__.py
drcrypt/crypt.py
drcrypt/hash.py
drcrypt/random.py
drcrypt-0.0.4.dist-info/LICENSE
drcrypt-0.0.4.dist-info/METADATA
drcrypt-0.0.4.dist-info/WHEEL
drcrypt-0.0.4.dist-info/top_level.txt
drcrypt-0.0.4.dist-info/RECORD
